Metadata-Version: 2.1
Name: SciFiPi
Version: 0.0.4
Summary: SciFiPi - The scientific filtering pipeline to clean your machine learning datasets
Home-page: https://github.com/GianMewes/KEEN
Author: HSU Institute of Automation
License: MIT
Download-URL: https://github.com/GianMewes/KEEN/archive/refs/tags/v0.0.4.tar.gz
Keywords: Data Preprocessing,Data Filtering,Machine Learning,AI,Data Science,python
Platform: UNKNOWN
Classifier: Development Status :: 3 - Alpha
Classifier: Intended Audience :: Developers
Classifier: Topic :: Software Development :: Build Tools
Classifier: License :: OSI Approved :: MIT License
Classifier: Programming Language :: Python :: 3
Classifier: Programming Language :: Python :: 3.4
Classifier: Programming Language :: Python :: 3.5
Classifier: Programming Language :: Python :: 3.6
Classifier: Programming Language :: Python :: 3.7
Classifier: Programming Language :: Python :: 3.8
Classifier: Programming Language :: Python :: 3.9
